graphic_coloring_engine/__init__.py
graphic_coloring_engine/core.py
graphic_coloring_engine/errors.py
graphic_coloring_engine/monkey_patching/__init__.py
graphic_coloring_engine/monkey_patching/colormath_contrast.py
graphic_coloring_engine/polygon.py
graphic_coloring_engine-0.1.9.dist-info/LICENSE
graphic_coloring_engine-0.1.9.dist-info/WHEEL
graphic_coloring_engine-0.1.9.dist-info/METADATA
graphic_coloring_engine-0.1.9.dist-info/RECORD
